twDaitaiMerge/__init__.py
twDaitaiMerge/__main__.py
twDaitaiMerge/merge.py
twDaitaiMerge/object.py
twDaitaiMerge-0.0.4.dist-info/LICENSE
twDaitaiMerge-0.0.4.dist-info/METADATA
twDaitaiMerge-0.0.4.dist-info/WHEEL
twDaitaiMerge-0.0.4.dist-info/top_level.txt
twDaitaiMerge-0.0.4.dist-info/RECORD
