Metadata-Version: 2.1
Name: twDaitaiMerge
Version: 0.0.4
Summary: A Python library for roughly merging Tailwind CSS class names.
Home-page: https://github.com/nojms-blue/twDaitaiMerge
Author: nOjms-Blue
License: MIT License
License-File: LICENSE
